[
  {
    "pag": 0,
    "x": 181,
    "y": 947,
    "w": 37,
    "h": 31,
    "score": 0.7388263940811157,
    "stddev": 60.508599907798605
  },
  {
    "pag": 0,
    "x": 181,
    "y": 983,
    "w": 37,
    "h": 31,
    "score": 0.9078032970428467,
    "stddev": 59.243379830578384
  },
  {
    "pag": 0,
    "x": 182,
    "y": 1019,
    "w": 37,
    "h": 31,
    "score": 0.7065207958221436,
    "stddev": 61.22911806536241
  },
  {
    "pag": 0,
    "x": 182,
    "y": 1056,
    "w": 37,
    "h": 31,
    "score": 0.6863457560539246,
    "stddev": 63.146662824398646
  },
  {
    "pag": 0,
    "x": 184,
    "y": 1093,
    "w": 34,
    "h": 28,
    "score": 0.7044956088066101,
    "stddev": 65.98042286307592
  },
  {
    "pag": 0,
    "x": 182,
    "y": 1271,
    "w": 37,
    "h": 31,
    "score": 0.6791572570800781,
    "stddev": 67.58280066823335
  },
  {
    "pag": 0,
    "x": 182,
    "y": 1307,
    "w": 37,
    "h": 31,
    "score": 0.7021949887275696,
    "stddev": 67.66869137097119
  },
  {
    "pag": 0,
    "x": 184,
    "y": 1648,
    "w": 37,
    "h": 31,
    "score": 0.917640209197998,
    "stddev": 70.53122067367076
  },
  {
    "pag": 0,
    "x": 187,
    "y": 1759,
    "w": 34,
    "h": 28,
    "score": 0.6909993886947632,
    "stddev": 92.43326108006896
  },
  {
    "pag": 0,
    "x": 185,
    "y": 1827,
    "w": 37,
    "h": 31,
    "score": 0.7579647302627563,
    "stddev": 73.46235252986928
  },
  {
    "pag": 0,
    "x": 185,
    "y": 1863,
    "w": 37,
    "h": 31,
    "score": 0.7561575770378113,
    "stddev": 73.92440912669144
  },
  {
    "pag": 0,
    "x": 185,
    "y": 1899,
    "w": 37,
    "h": 31,
    "score": 0.7301588654518127,
    "stddev": 74.56537655776222
  },
  {
    "pag": 1,
    "x": 180,
    "y": 328,
    "w": 37,
    "h": 31,
    "score": 0.759435772895813,
    "stddev": 62.48750696781977
  },
  {
    "pag": 1,
    "x": 181,
    "y": 365,
    "w": 37,
    "h": 31,
    "score": 0.8589913845062256,
    "stddev": 60.18243211712622
  },
  {
    "pag": 1,
    "x": 182,
    "y": 401,
    "w": 37,
    "h": 31,
    "score": 0.8555276393890381,
    "stddev": 59.48137511593844
  },
  {
    "pag": 1,
    "x": 182,
    "y": 656,
    "w": 37,
    "h": 31,
    "score": 0.7309738993644714,
    "stddev": 54.875417502001675
  },
  {
    "pag": 1,
    "x": 182,
    "y": 692,
    "w": 37,
    "h": 31,
    "score": 0.913511335849762,
    "stddev": 54.61648912056532
  },
  {
    "pag": 1,
    "x": 182,
    "y": 728,
    "w": 37,
    "h": 31,
    "score": 0.7413080930709839,
    "stddev": 54.4913044583709
  },
  {
    "pag": 1,
    "x": 184,
    "y": 765,
    "w": 34,
    "h": 28,
    "score": 0.9022045731544495,
    "stddev": 56.132352003082175
  },
  {
    "pag": 1,
    "x": 183,
    "y": 799,
    "w": 37,
    "h": 31,
    "score": 0.7681351900100708,
    "stddev": 56.67119895595925
  },
  {
    "pag": 1,
    "x": 185,
    "y": 1057,
    "w": 37,
    "h": 31,
    "score": 0.9268918037414551,
    "stddev": 60.13549473748539
  },
  {
    "pag": 1,
    "x": 185,
    "y": 1093,
    "w": 37,
    "h": 31,
    "score": 0.9144878387451172,
    "stddev": 58.659386374766434
  },
  {
    "pag": 1,
    "x": 187,
    "y": 1130,
    "w": 34,
    "h": 28,
    "score": 0.9037345051765442,
    "stddev": 62.20559477680711
  },
  {
    "pag": 1,
    "x": 186,
    "y": 1164,
    "w": 37,
    "h": 31,
    "score": 0.7410032153129578,
    "stddev": 62.32168884280285
  },
  {
    "pag": 1,
    "x": 190,
    "y": 1646,
    "w": 34,
    "h": 28,
    "score": 0.9043699502944946,
    "stddev": 69.24692525611232
  },
  {
    "pag": 1,
    "x": 189,
    "y": 1680,
    "w": 37,
    "h": 31,
    "score": 0.9308901429176331,
    "stddev": 66.35685311310186
  },
  {
    "pag": 1,
    "x": 189,
    "y": 1716,
    "w": 37,
    "h": 31,
    "score": 0.9183708429336548,
    "stddev": 68.2680925681222
  },
  {
    "pag": 1,
    "x": 191,
    "y": 1753,
    "w": 34,
    "h": 28,
    "score": 0.7097872495651245,
    "stddev": 68.84993848858801
  },
  {
    "pag": 1,
    "x": 192,
    "y": 1788,
    "w": 34,
    "h": 28,
    "score": 0.7165226936340332,
    "stddev": 67.98048785637178
  },
  {
    "pag": 1,
    "x": 190,
    "y": 1822,
    "w": 37,
    "h": 31,
    "score": 0.9121242165565491,
    "stddev": 64.46483999809158
  },
  {
    "pag": 2,
    "x": 189,
    "y": 461,
    "w": 34,
    "h": 28,
    "score": 0.8346344232559204,
    "stddev": 57.86348623307261
  },
  {
    "pag": 2,
    "x": 189,
    "y": 496,
    "w": 34,
    "h": 28,
    "score": 0.8081855177879333,
    "stddev": 59.533633550715386
  },
  {
    "pag": 2,
    "x": 188,
    "y": 530,
    "w": 37,
    "h": 31,
    "score": 0.8278836607933044,
    "stddev": 57.18478055699219
  },
  {
    "pag": 2,
    "x": 190,
    "y": 567,
    "w": 34,
    "h": 28,
    "score": 0.8362051248550415,
    "stddev": 52.79645491192033
  },
  {
    "pag": 2,
    "x": 188,
    "y": 601,
    "w": 37,
    "h": 31,
    "score": 0.8214436173439026,
    "stddev": 57.475501379072355
  },
  {
    "pag": 2,
    "x": 188,
    "y": 637,
    "w": 37,
    "h": 31,
    "score": 0.7504704594612122,
    "stddev": 56.92834357526592
  },
  {
    "pag": 2,
    "x": 188,
    "y": 672,
    "w": 37,
    "h": 31,
    "score": 0.7616569399833679,
    "stddev": 56.42259216567365
  },
  {
    "pag": 2,
    "x": 188,
    "y": 708,
    "w": 37,
    "h": 31,
    "score": 0.8986472487449646,
    "stddev": 55.87189773422473
  },
  {
    "pag": 2,
    "x": 189,
    "y": 745,
    "w": 34,
    "h": 28,
    "score": 0.8921939134597778,
    "stddev": 57.08615309825224
  },
  {
    "pag": 2,
    "x": 188,
    "y": 780,
    "w": 34,
    "h": 28,
    "score": 0.9276842474937439,
    "stddev": 55.15622895440358
  },
  {
    "pag": 2,
    "x": 189,
    "y": 1098,
    "w": 34,
    "h": 28,
    "score": 0.7382116913795471,
    "stddev": 62.384203292301684
  },
  {
    "pag": 2,
    "x": 188,
    "y": 1132,
    "w": 37,
    "h": 31,
    "score": 0.89214688539505,
    "stddev": 62.63255670774363
  },
  {
    "pag": 2,
    "x": 188,
    "y": 1167,
    "w": 37,
    "h": 31,
    "score": 0.9084449410438538,
    "stddev": 63.016405380454515
  },
  {
    "pag": 2,
    "x": 189,
    "y": 1204,
    "w": 34,
    "h": 28,
    "score": 0.8833820223808289,
    "stddev": 66.68281842213722
  },
  {
    "pag": 2,
    "x": 187,
    "y": 1238,
    "w": 37,
    "h": 31,
    "score": 0.9171537756919861,
    "stddev": 63.26676920939066
  },
  {
    "pag": 2,
    "x": 220,
    "y": 1722,
    "w": 37,
    "h": 31,
    "score": 0.6847216486930847,
    "stddev": 68.89934259634784
  }
]